{
  "msft-short-put-jul17:CRITICAL": "2026-06-23T16:03:05.698591",
  "msft-short-put-aug21:WARNING": "2026-06-30T19:19:08.054999",
  "nvda-short-put-jul17:WARNING": "2026-07-03T15:11:15.549212",
  "msft-short-put-aug21:CRITICAL": "2026-06-25T21:15:52.407394",
  "nvda-short-put-jul17:CRITICAL": "2026-07-02T18:48:35.541549",
  "goog-short-put-aug21:WARNING": "2026-06-26T21:06:21.146710",
  "tlt-covered-call-aug21:WARNING": "2026-07-03T15:11:17.482425",
  "aapl-covered-call-aug21:BREACHED": "2026-07-03T15:11:17.827294",
  "avgo-short-put-jul17:WARNING": "2026-07-03T15:11:16.857440"
}