{
  "updated_at": "2026-07-09T19:55:07.651636Z",
  "positions": [
    {
      "id": "nvda-short-put-aug21",
      "ticker": "NVDA",
      "strategy": "Short Put",
      "strike": 190,
      "expiry": "2026-08-21",
      "premium_collected": 5.8,
      "contracts": 1,
      "open_date": "2026-06-05",
      "newsletter": "Growth Gazette",
      "rating": "A",
      "notes": "Rolled from $200 Jul 17 to $190 Aug 21 for $0.50 debit \u2014 breakeven ~$184.20",
      "current_price": 203.43,
      "option_data": {
        "bid": 5.0,
        "ask": 5.1,
        "last": 5.0,
        "iv": 38.5,
        "volume": 2150,
        "expiry_used": "2026-08-21"
      },
      "status": {
        "breakeven": 184.2,
        "breakeven_label": "$184.20",
        "distance_pct": 10.439739413680792,
        "alert_level": "OK",
        "message": "Stock $203.43 is 10.4% above breakeven $184.20. Safe.",
        "risk_direction": "downside"
      }
    },
    {
      "id": "orcl-covered-call-jul17",
      "ticker": "ORCL",
      "strategy": "Covered Call",
      "strike": 260,
      "expiry": "2026-07-17",
      "premium_collected": 9.4,
      "contracts": 1,
      "open_date": "2026-06-01",
      "newsletter": "Growth Gazette",
      "rating": "C",
      "notes": "Sell $260 Call Jul 17",
      "current_price": 144.06,
      "option_data": {
        "bid": 0.0,
        "ask": 0.01,
        "last": 0.01,
        "iv": 115.6,
        "volume": 231,
        "expiry_used": "2026-07-17"
      },
      "status": {
        "breakeven": 260,
        "breakeven_label": "$260.00 (call strike)",
        "distance_pct": 44.59230769230769,
        "alert_level": "OK",
        "message": "Stock $144.06 is 44.6% below strike $260.00. Call not threatened.",
        "risk_direction": "upside"
      }
    },
    {
      "id": "goog-short-put-aug21",
      "ticker": "GOOG",
      "strategy": "Short Put",
      "strike": 340,
      "expiry": "2026-08-21",
      "premium_collected": 11.7,
      "contracts": 1,
      "open_date": "2026-06-09",
      "newsletter": "Growth Gazette",
      "rating": "C",
      "notes": "Sell $340 Put Aug 21",
      "current_price": 356.44,
      "option_data": {
        "bid": 10.5,
        "ask": 11.15,
        "last": 11.03,
        "iv": 37.8,
        "volume": 109,
        "expiry_used": "2026-08-21"
      },
      "status": {
        "breakeven": 328.3,
        "breakeven_label": "$328.30",
        "distance_pct": 8.571428571428568,
        "alert_level": "OK",
        "message": "Stock $356.44 is 8.6% above breakeven $328.30. Safe.",
        "risk_direction": "downside"
      }
    },
    {
      "id": "msft-short-put-aug21",
      "ticker": "MSFT",
      "strategy": "Short Put",
      "strike": 375,
      "expiry": "2026-08-21",
      "premium_collected": 10.6,
      "contracts": 1,
      "open_date": "2026-06-09",
      "newsletter": "Growth Gazette",
      "rating": "C",
      "notes": "Rolled from $390 Jul 17 to $375 Aug 21 \u2014 breakeven ~$364.40",
      "current_price": 384.49,
      "option_data": {
        "bid": 16.95,
        "ask": 17.3,
        "last": 17.09,
        "iv": 41.3,
        "volume": 157,
        "expiry_used": "2026-08-21"
      },
      "status": {
        "breakeven": 364.4,
        "breakeven_label": "$364.40",
        "distance_pct": 5.51317233809002,
        "alert_level": "OK",
        "message": "Stock $384.49 is 5.5% above breakeven $364.40. Safe.",
        "risk_direction": "downside"
      }
    },
    {
      "id": "hims-covered-call-aug21",
      "ticker": "HIMS",
      "strategy": "Covered Call",
      "strike": 40,
      "expiry": "2026-08-21",
      "premium_collected": 5.5,
      "contracts": 1,
      "open_date": "2026-07-01",
      "newsletter": "Growth Gazette",
      "rating": "C",
      "notes": "Sell $40 Call Aug 21 \u2014 breakeven ~$45.50",
      "current_price": 35.42,
      "option_data": {
        "bid": 3.65,
        "ask": 3.8,
        "last": 3.8,
        "iv": 110.4,
        "volume": 1106,
        "expiry_used": "2026-08-21"
      },
      "status": {
        "breakeven": 40,
        "breakeven_label": "$40.00 (call strike)",
        "distance_pct": 11.449999999999996,
        "alert_level": "OK",
        "message": "Stock $35.42 is 11.4% below strike $40.00. Call not threatened.",
        "risk_direction": "upside"
      }
    },
    {
      "id": "aapl-covered-call-aug21",
      "ticker": "AAPL",
      "strategy": "Covered Call",
      "strike": 260,
      "expiry": "2026-08-21",
      "premium_collected": 6.9,
      "contracts": 1,
      "open_date": "2026-06-18",
      "newsletter": "Income Insider",
      "rating": "B",
      "notes": "Sell $260 Call Aug 21 \u2014 avg price $6.90",
      "current_price": 316.51,
      "option_data": {
        "bid": 56.9,
        "ask": 57.65,
        "last": 56.9,
        "iv": 38.2,
        "volume": 38,
        "expiry_used": "2026-08-21"
      },
      "status": {
        "breakeven": 260,
        "breakeven_label": "$260.00 (call strike)",
        "distance_pct": -21.73461538461538,
        "alert_level": "BREACHED",
        "message": "\ud83d\udea8 BREACHED: Stock $316.51 is 21.7% above call strike $260.00. Deep ITM \u2014 shares likely called away at expiry.",
        "risk_direction": "upside"
      }
    },
    {
      "id": "aapl-covered-call-320-aug21",
      "ticker": "AAPL",
      "strategy": "Covered Call",
      "strike": 320,
      "expiry": "2026-08-21",
      "premium_collected": 10.0,
      "contracts": 1,
      "open_date": "2026-07-06",
      "newsletter": "Growth Gazette",
      "rating": "B",
      "notes": "Sell $320 Call Aug 21",
      "current_price": 316.51,
      "option_data": {
        "bid": 9.75,
        "ask": 9.95,
        "last": 9.82,
        "iv": 26.4,
        "volume": 1461,
        "expiry_used": "2026-08-21"
      },
      "status": {
        "breakeven": 320,
        "breakeven_label": "$320.00 (call strike)",
        "distance_pct": 1.0906250000000028,
        "alert_level": "WARNING",
        "message": "\u26a0\ufe0f Stock $316.51 is within 1.1% of call strike $320.00. Risk of assignment approaching.",
        "risk_direction": "upside"
      }
    },
    {
      "id": "asts-short-put-aug21",
      "ticker": "ASTS",
      "strategy": "Short Put",
      "strike": 80,
      "expiry": "2026-08-21",
      "premium_collected": 11.4,
      "contracts": 1,
      "open_date": "2026-07-06",
      "newsletter": "Growth Gazette",
      "rating": "C",
      "notes": "Sell $80 Put Aug 21 \u2014 breakeven ~$68.60",
      "current_price": 73.53,
      "option_data": {
        "bid": 13.7,
        "ask": 14.0,
        "last": 13.95,
        "iv": 97.3,
        "volume": 218,
        "expiry_used": "2026-08-21"
      },
      "status": {
        "breakeven": 68.6,
        "breakeven_label": "$68.60",
        "distance_pct": 7.186588921282809,
        "alert_level": "OK",
        "message": "Stock $73.53 is 7.2% above breakeven $68.60. Safe.",
        "risk_direction": "downside"
      }
    }
  ]
}