{
  "updated_at": "2026-07-03T19:51:13.308595Z",
  "positions": [
    {
      "id": "nvda-short-put-jul17",
      "ticker": "NVDA",
      "strategy": "Short Put",
      "strike": 200,
      "expiry": "2026-07-17",
      "premium_collected": 6.3,
      "contracts": 1,
      "open_date": "2026-06-05",
      "newsletter": "Growth Gazette",
      "rating": "A",
      "notes": "Sell $200 Put Jul 17",
      "current_price": 194.83,
      "option_data": {
        "bid": 8.6,
        "ask": 8.9,
        "last": 8.65,
        "iv": 37.4,
        "volume": 4465,
        "expiry_used": "2026-07-17"
      },
      "status": {
        "breakeven": 193.7,
        "breakeven_label": "$193.70",
        "distance_pct": 0.583376355188448,
        "alert_level": "WARNING",
        "message": "\u26a0\ufe0f Stock $194.83 is within 0.6% of breakeven $193.70. Monitor closely.",
        "risk_direction": "downside"
      }
    },
    {
      "id": "orcl-covered-call-jul17",
      "ticker": "ORCL",
      "strategy": "Covered Call",
      "strike": 260,
      "expiry": "2026-07-17",
      "premium_collected": 9.4,
      "contracts": 1,
      "open_date": "2026-06-01",
      "newsletter": "Growth Gazette",
      "rating": "C",
      "notes": "Sell $260 Call Jul 17",
      "current_price": 140.27,
      "option_data": {
        "bid": 0.01,
        "ask": 0.06,
        "last": 0.04,
        "iv": 109.8,
        "volume": 122,
        "expiry_used": "2026-07-17"
      },
      "status": {
        "breakeven": 260,
        "breakeven_label": "$260.00 (call strike)",
        "distance_pct": 46.05,
        "alert_level": "OK",
        "message": "Stock $140.27 is 46.0% below strike $260.00. Call not threatened.",
        "risk_direction": "upside"
      }
    },
    {
      "id": "goog-short-put-aug21",
      "ticker": "GOOG",
      "strategy": "Short Put",
      "strike": 340,
      "expiry": "2026-08-21",
      "premium_collected": 11.7,
      "contracts": 1,
      "open_date": "2026-06-09",
      "newsletter": "Growth Gazette",
      "rating": "C",
      "notes": "Sell $340 Put Aug 21",
      "current_price": 356.18,
      "option_data": {
        "bid": 10.75,
        "ask": 11.8,
        "last": 11.61,
        "iv": 36.6,
        "volume": 127,
        "expiry_used": "2026-08-21"
      },
      "status": {
        "breakeven": 328.3,
        "breakeven_label": "$328.30",
        "distance_pct": 8.492232713981112,
        "alert_level": "OK",
        "message": "Stock $356.18 is 8.5% above breakeven $328.30. Safe.",
        "risk_direction": "downside"
      }
    },
    {
      "id": "msft-short-put-aug21",
      "ticker": "MSFT",
      "strategy": "Short Put",
      "strike": 375,
      "expiry": "2026-08-21",
      "premium_collected": 10.6,
      "contracts": 1,
      "open_date": "2026-06-09",
      "newsletter": "Growth Gazette",
      "rating": "C",
      "notes": "Rolled from $390 Jul 17 to $375 Aug 21 \u2014 breakeven ~$364.40",
      "current_price": 390.49,
      "option_data": {
        "bid": 14.45,
        "ask": 15.35,
        "last": 15.0,
        "iv": 39.4,
        "volume": 800,
        "expiry_used": "2026-08-21"
      },
      "status": {
        "breakeven": 364.4,
        "breakeven_label": "$364.40",
        "distance_pct": 7.159714599341392,
        "alert_level": "OK",
        "message": "Stock $390.49 is 7.2% above breakeven $364.40. Safe.",
        "risk_direction": "downside"
      }
    },
    {
      "id": "avgo-short-put-jul17",
      "ticker": "AVGO",
      "strategy": "Short Put",
      "strike": 370,
      "expiry": "2026-07-17",
      "premium_collected": 16.0,
      "contracts": 1,
      "open_date": "2026-06-26",
      "newsletter": "Growth Gazette",
      "rating": "C",
      "notes": "Sell $370 Put Jul 17 \u2014 breakeven ~$354.00",
      "current_price": 360.45,
      "option_data": {
        "bid": 18.35,
        "ask": 19.6,
        "last": 19.03,
        "iv": 48.5,
        "volume": 908,
        "expiry_used": "2026-07-17"
      },
      "status": {
        "breakeven": 354.0,
        "breakeven_label": "$354.00",
        "distance_pct": 1.8220338983050817,
        "alert_level": "WARNING",
        "message": "\u26a0\ufe0f Stock $360.45 is within 1.8% of breakeven $354.00. Monitor closely.",
        "risk_direction": "downside"
      }
    },
    {
      "id": "hims-covered-call-aug21",
      "ticker": "HIMS",
      "strategy": "Covered Call",
      "strike": 40,
      "expiry": "2026-08-21",
      "premium_collected": 5.5,
      "contracts": 1,
      "open_date": "2026-07-01",
      "newsletter": "Growth Gazette",
      "rating": "C",
      "notes": "Sell $40 Call Aug 21 \u2014 breakeven ~$45.50",
      "current_price": 36.8,
      "option_data": {
        "bid": 4.55,
        "ask": 4.75,
        "last": 4.67,
        "iv": 108.7,
        "volume": 1143,
        "expiry_used": "2026-08-21"
      },
      "status": {
        "breakeven": 40,
        "breakeven_label": "$40.00 (call strike)",
        "distance_pct": 8.000000000000007,
        "alert_level": "OK",
        "message": "Stock $36.80 is 8.0% below strike $40.00. Call not threatened.",
        "risk_direction": "upside"
      }
    },
    {
      "id": "tlt-covered-call-aug21",
      "ticker": "TLT",
      "strategy": "Covered Call",
      "strike": 87,
      "expiry": "2026-08-21",
      "premium_collected": 1.05,
      "contracts": 1,
      "open_date": "2026-06-17",
      "newsletter": "Income Insider",
      "rating": "AA",
      "notes": "Sell $87 Call Aug 21 \u2014 avg price $1.05",
      "current_price": 85.51,
      "option_data": {
        "bid": 0.59,
        "ask": 0.61,
        "last": 0.61,
        "iv": 9.5,
        "volume": 839,
        "expiry_used": "2026-08-21"
      },
      "status": {
        "breakeven": 87,
        "breakeven_label": "$87.00 (call strike)",
        "distance_pct": 1.7126436781609138,
        "alert_level": "WARNING",
        "message": "\u26a0\ufe0f Stock $85.51 is within 1.7% of call strike $87.00. Risk of assignment approaching.",
        "risk_direction": "upside"
      }
    },
    {
      "id": "aapl-covered-call-aug21",
      "ticker": "AAPL",
      "strategy": "Covered Call",
      "strike": 260,
      "expiry": "2026-08-21",
      "premium_collected": 6.9,
      "contracts": 1,
      "open_date": "2026-06-18",
      "newsletter": "Income Insider",
      "rating": "B",
      "notes": "Sell $260 Call Aug 21 \u2014 avg price $6.90",
      "current_price": 308.63,
      "option_data": {
        "bid": 50.1,
        "ask": 52.1,
        "last": 50.08,
        "iv": 44.0,
        "volume": 68,
        "expiry_used": "2026-08-21"
      },
      "status": {
        "breakeven": 260,
        "breakeven_label": "$260.00 (call strike)",
        "distance_pct": -18.70384615384615,
        "alert_level": "BREACHED",
        "message": "\ud83d\udea8 BREACHED: Stock $308.63 is 18.7% above call strike $260.00. Deep ITM \u2014 shares likely called away at expiry.",
        "risk_direction": "upside"
      }
    },
    {
      "id": "nke-covered-call-aug21",
      "ticker": "NKE",
      "strategy": "Covered Call",
      "strike": 47.5,
      "expiry": "2026-08-21",
      "premium_collected": 4.0,
      "contracts": 1,
      "open_date": "2026-05-29",
      "newsletter": "Income Insider",
      "rating": "B",
      "notes": "Sell $47.5 Call Aug 21 \u2014 avg price $4.00",
      "current_price": 44.09,
      "option_data": {
        "bid": 1.17,
        "ask": 1.21,
        "last": 1.2,
        "iv": 37.9,
        "volume": 1042,
        "expiry_used": "2026-08-21"
      },
      "status": {
        "breakeven": 47.5,
        "breakeven_label": "$47.50 (call strike)",
        "distance_pct": 7.178947368421046,
        "alert_level": "OK",
        "message": "Stock $44.09 is 7.2% below strike $47.50. Call not threatened.",
        "risk_direction": "upside"
      }
    }
  ]
}